{
  "articles": [
    {
      "id": 1,
      "title": "Hà Nội muốn phá dỡ tập thể 56 tuổi ở Trương Định để xây chung cư cao tầng",
      "summary": "<a href=\"https://dantri.com.vn/bat-dong-san/ha-noi-muon-pha-do-tap-the-56-tuoi-o-truong-dinh-de-xay-chung-cu-cao-tang-20260715151137062.htm\"><img src=\"https://icdn.dantri.com.vn/2026/07/15/tap-the-quan-ba-dinh-xuong-capthanh-dong-38-1741766283477-1784103024979.jpg\" /></a>(Dân trí) - Hà Nội vừa công bố quy hoạch cải tạo, xây dựng lại khu tập thể Trương Định với 2 tòa chung cư cao tối đa 30 tầng, dự kiến bố trí khoảng 1.065 căn hộ."
    },
    {
      "id": 2,
      "title": "Tổng thống Trump để ngỏ chiến dịch trên bộ, chiếm đảo huyết mạch của Iran",
      "summary": "<a href=\"https://dantri.com.vn/the-gioi/tong-thong-trump-de-ngo-chien-dich-tren-bo-chiem-dao-huyet-mach-cua-iran-20260715150601811.htm\"><img src=\"https://icdn.dantri.com.vn/2026/07/15/linh-my-huan-luyen-do-bogetty-1784101691301.png\" /></a>(Dân trí) - Tổng thống Mỹ Donald Trump không loại trừ khả năng mở chiến dịch tấn công trên bộ vào Iran, tuy nhiên kế hoạch này sẽ đối mặt với nhiều thách thức."
    },
    {
      "id": 3,
      "title": "Diễn biến mới ở \"phố kim cương\": Khuyên khách bán kim cương, đổi sang vàng",
      "summary": "<a href=\"https://dantri.com.vn/kinh-doanh/dien-bien-moi-o-pho-kim-cuong-khuyen-khach-ban-kim-cuong-doi-sang-vang-20260715131923021.htm\"><img src=\"https://icdn.dantri.com.vn/2026/06/26/kim-cuong-cropped-1782461464955.jpg\" /></a>(Dân trí) - Phố tập trung nhiều cửa hàng kim cương tại TPHCM đang ghi nhận diễn biến: một số vẫn mở, trong khi số khác đóng im lìm. Khách bán lại kim cương được khuyến khích đổi sang vàng, mua lại bằng 90% giá."
    }
  ]
}