{
  "articles": [
    {
      "id": 1,
      "title": "122 cán bộ không chuyên trách trúng tuyển công chức",
      "summary": "<a href=\"https://dantri.com.vn/noi-vu/122-can-bo-khong-chuyen-trach-trung-tuyen-cong-chuc-20260605154117989.htm\"><img src=\"https://icdn.dantri.com.vn/2026/06/05/can-bo-xa-binh-minhdanh-tue-edited-1780648004757.jpg\" /></a>(Dân trí) - UBND các xã trên địa bàn tỉnh Nghệ An được bổ sung 112 công chức là người hoạt động không chuyên trách. Riêng xã Bình Minh được bổ sung nhân sự nhiều nhất vào bộ máy với 8 công chức."
    },
    {
      "id": 2,
      "title": "Vàng SJC liên tiếp giảm sâu, giá mua vào chỉ còn 149,2 triệu đồng/lượng",
      "summary": "<a href=\"https://dantri.com.vn/kinh-doanh/vang-sjc-lien-tiep-giam-sau-gia-mua-vao-chi-con-1492-trieu-dongluong-20260606072048638.htm\"><img src=\"https://icdn.dantri.com.vn/2024/05/03/mua-vang-crop-1714710703853.jpeg\" /></a>(Dân trí) - Trên thế giới, vàng giao ngay cũng giảm mạnh 140 USD/ounce chỉ sau 1 đêm. Vàng miếng SJC hiện chỉ còn 149,2-153,2 triệu đồng/lượng (mua vào - bán ra), giảm hơn 38 triệu đồng/lượng từ đầu năm."
    },
    {
      "id": 3,
      "title": "Nghệ An dự kiến giảm 1.771 thôn, xóm sau sắp xếp",
      "summary": "<a href=\"https://dantri.com.vn/noi-vu/nghe-an-du-kien-giam-1771-thon-xom-sau-sap-xep-20260605111923213.htm\"><img src=\"https://icdn.dantri.com.vn/2024/05/25/43879659533008385000598691872303374925924860n-edited-1716622784926.jpeg\" /></a>(Dân trí) - Theo phương án đề xuất, tỉnh Nghệ An sắp xếp từ 3.797 khối, xóm hiện có thành 2.026 khối, xóm mới, giảm 1.771 khối, xóm."
    }
  ]
}